Metadata-Version: 1.1
Name: selenium-unittest
Version: 0.1.2
Summary: Selenium Unit Test Framework
Home-page: https://github.com/agramian/selenium-unittest
Author: Abtin Gramian
Author-email: abtin.gramian@gmail.com
License: UNKNOWN
Download-URL: https://github.com/agramian/selenium-unittest/tarball/v0.1.2
Keywords: selenium,unittest,unit,test,testing
Platform: UNKNOWN
